mdtablegen/__init__.py
mdtablegen/divfactory.py
mdtablegen/layout.py
mdtablegen/render.py
mdtablegen/rowfactory.py
mdtablegen/table.py
mdtablegen-1.0.2.dist-info/LICENSE
mdtablegen-1.0.2.dist-info/METADATA
mdtablegen-1.0.2.dist-info/WHEEL
mdtablegen-1.0.2.dist-info/top_level.txt
mdtablegen-1.0.2.dist-info/RECORD
