Metadata-Version: 2.1
Name: mdtablegen
Version: 1.0.2
Summary: A Markdown Table Generator
Author-email: Steve Benson <steve@xelphene.net>
Project-URL: Homepage, https://github.com/xelphene/mdtablegen
Project-URL: Bug Tracker, https://github.com/xelphene/mdtablegen/issues
Classifier: Programming Language :: Python :: 3
Classifier: License :: OSI Approved :: GNU General Public License v3 (GPLv3)
Classifier: Operating System :: OS Independent
Requires-Python: >=3.7
License-File: LICENSE
